{
  "$schema": "https://developer.microsoft.com/json-schemas/fabric/item/report/definition/visualContainer/2.1.0/schema.json",
  "name": "d3189d92a9ce4e19fd69",
  "position": {
    "x": 218.20395738203956,
    "y": 16.560121765601217,
    "z": 9000,
    "height": 37.016742770167426,
    "width": 356.52968036529677,
    "tabOrder": 10000
  },
  "visual": {
    "visualType": "textbox",
    "objects": {
      "general": [
        {
          "properties": {
            "paragraphs": [
              {
                "textRuns": [
                  {
                    "value": "Note:   *** ",
                    "textStyle": {
                      "fontWeight": "bold",
                      "fontSize": "14pt"
                    }
                  },
                  {
                    "value": "Sensitive Information ",
                    "textStyle": {
                      "fontWeight": "bold",
                      "fontSize": "14pt",
                      "color": "#fa0404"
                    }
                  },
                  {
                    "value": " ***",
                    "textStyle": {
                      "fontWeight": "bold",
                      "fontSize": "14pt"
                    }
                  }
                ]
              }
            ]
          }
        }
      ]
    },
    "visualContainerObjects": {
      "background": [
        {
          "properties": {
            "show": {
              "expr": {
                "Literal": {
                  "Value": "false"
                }
              }
            }
          }
        }
      ]
    },
    "drillFilterOtherVisuals": true
  }
}