{
  "$schema": "https://developer.microsoft.com/json-schemas/fabric/item/report/definition/visualContainer/2.1.0/schema.json",
  "name": "018a6408040847705343",
  "position": {
    "x": 374,
    "y": 65,
    "z": 3000,
    "height": 29.223744292237441,
    "width": 40.913242009132418,
    "tabOrder": 3000
  },
  "visual": {
    "visualType": "image",
    "objects": {
      "general": [
        {
          "properties": {
            "imageUrl": {
              "expr": {
                "ResourcePackageItem": {
                  "PackageName": "RegisteredResources",
                  "PackageType": 1,
                  "ItemName": "check29123191888170874.png"
                }
              }
            }
          }
        }
      ]
    },
    "visualContainerObjects": {
      "title": [
        {
          "properties": {
            "text": {
              "expr": {
                "Literal": {
                  "Value": "'Tick Daily'"
                }
              }
            }
          }
        }
      ]
    },
    "drillFilterOtherVisuals": true
  },
  "howCreated": "InsertVisualButton"
}