{
  "$schema": "https://developer.microsoft.com/json-schemas/fabric/item/report/definition/visualContainer/2.1.0/schema.json",
  "name": "19842f4cb25ed1b86087",
  "position": {
    "x": 363.59102244389027,
    "y": 73.615960099750623,
    "z": 3000,
    "height": 52.069825436408976,
    "width": 71.820448877805489,
    "tabOrder": 3000
  },
  "visual": {
    "visualType": "advancedSlicerVisual",
    "query": {
      "queryState": {
        "Values": {
          "projections": [
            {
              "field": {
                "Column": {
                  "Expression": {
                    "SourceRef": {
                      "Entity": "Date Table"
                    }
                  },
                  "Property": "Actual Only"
                }
              },
              "queryRef": "Date Table.Only Forecast",
              "nativeQueryRef": "Actual Values Only",
              "displayName": "Actual Values Only"
            }
          ]
        }
      }
    },
    "objects": {
      "data": [
        {
          "properties": {}
        }
      ],
      "general": [
        {
          "properties": {
            "filter": {
              "filter": {
                "Version": 2,
                "From": [
                  {
                    "Name": "d",
                    "Entity": "Date Table",
                    "Type": 0
                  }
                ],
                "Where": [
                  {
                    "Condition": {
                      "In": {
                        "Expressions": [
                          {
                            "Column": {
                              "Expression": {
                                "SourceRef": {
                                  "Source": "d"
                                }
                              },
                              "Property": "Actual Only"
                            }
                          }
                        ],
                        "Values": [
                          [
                            {
                              "Literal": {
                                "Value": "'Forecast'"
                              }
                            }
                          ],
                          [
                            {
                              "Literal": {
                                "Value": "'Actual'"
                              }
                            }
                          ]
                        ]
                      }
                    }
                  }
                ]
              }
            }
          }
        }
      ],
      "padding": [
        {
          "properties": {
            "paddingSelection": {
              "expr": {
                "Literal": {
                  "Value": "'Narrow'"
                }
              }
            }
          },
          "selector": {
            "id": "default"
          }
        }
      ],
      "value": [
        {
          "properties": {
            "horizontalAlignment": {
              "expr": {
                "Literal": {
                  "Value": "'center'"
                }
              }
            },
            "fontSize": {
              "expr": {
                "Literal": {
                  "Value": "8D"
                }
              }
            },
            "bold": {
              "expr": {
                "Literal": {
                  "Value": "false"
                }
              }
            }
          },
          "selector": {
            "id": "default"
          }
        },
        {
          "properties": {
            "show": {
              "expr": {
                "Literal": {
                  "Value": "true"
                }
              }
            }
          }
        }
      ],
      "layout": [
        {
          "properties": {
            "rowCount": {
              "expr": {
                "Literal": {
                  "Value": "2L"
                }
              }
            },
            "columnCount": {
              "expr": {
                "Literal": {
                  "Value": "1L"
                }
              }
            },
            "cellPadding": {
              "expr": {
                "Literal": {
                  "Value": "4L"
                }
              }
            }
          }
        }
      ],
      "outline": [
        {
          "properties": {
            "show": {
              "expr": {
                "Literal": {
                  "Value": "true"
                }
              }
            }
          },
          "selector": {
            "id": "default"
          }
        },
        {
          "properties": {
            "show": {
              "expr": {
                "Literal": {
                  "Value": "true"
                }
              }
            },
            "lineColor": {
              "solid": {
                "color": {
                  "expr": {
                    "ThemeDataColor": {
                      "ColorId": 0,
                      "Percent": -0.3
                    }
                  }
                }
              }
            }
          },
          "selector": {
            "id": "selection:selected"
          }
        }
      ],
      "fillCustom": [
        {
          "properties": {
            "show": {
              "expr": {
                "Literal": {
                  "Value": "true"
                }
              }
            }
          }
        },
        {
          "properties": {
            "fillColor": {
              "solid": {
                "color": {
                  "expr": {
                    "ThemeDataColor": {
                      "ColorId": 6,
                      "Percent": -0.25
                    }
                  }
                }
              }
            }
          },
          "selector": {
            "id": "selection:selected"
          }
        }
      ],
      "label": [
        {
          "properties": {
            "show": {
              "expr": {
                "Literal": {
                  "Value": "false"
                }
              }
            }
          },
          "selector": {
            "id": "default"
          }
        }
      ],
      "selectionIcon": [
        {
          "properties": {
            "show": {
              "expr": {
                "Literal": {
                  "Value": "false"
                }
              }
            }
          }
        }
      ],
      "selection": [
        {
          "properties": {
            "strictSingleSelect": {
              "expr": {
                "Literal": {
                  "Value": "false"
                }
              }
            },
            "singleSelect": {
              "expr": {
                "Literal": {
                  "Value": "false"
                }
              }
            }
          }
        }
      ]
    },
    "visualContainerObjects": {
      "visualHeader": [
        {
          "properties": {
            "show": {
              "expr": {
                "Literal": {
                  "Value": "false"
                }
              }
            }
          }
        }
      ],
      "title": [
        {
          "properties": {
            "heading": {
              "expr": {
                "Literal": {
                  "Value": "'Normal'"
                }
              }
            },
            "fontSize": {
              "expr": {
                "Literal": {
                  "Value": "8D"
                }
              }
            },
            "alignment": {
              "expr": {
                "Literal": {
                  "Value": "'center'"
                }
              }
            },
            "show": {
              "expr": {
                "Literal": {
                  "Value": "false"
                }
              }
            }
          }
        }
      ],
      "padding": [
        {
          "properties": {
            "left": {
              "expr": {
                "Literal": {
                  "Value": "2D"
                }
              }
            },
            "bottom": {
              "expr": {
                "Literal": {
                  "Value": "2D"
                }
              }
            },
            "right": {
              "expr": {
                "Literal": {
                  "Value": "2D"
                }
              }
            }
          }
        }
      ],
      "background": [
        {
          "properties": {
            "show": {
              "expr": {
                "Literal": {
                  "Value": "false"
                }
              }
            }
          }
        }
      ]
    },
    "drillFilterOtherVisuals": true
  },
  "filterConfig": {
    "filters": [
      {
        "name": "601ad0916aa102bb31e2",
        "field": {
          "Column": {
            "Expression": {
              "SourceRef": {
                "Entity": "Date Table"
              }
            },
            "Property": "Actual Only"
          }
        },
        "type": "Categorical",
        "filter": {
          "Version": 2,
          "From": [
            {
              "Name": "d",
              "Entity": "Date Table",
              "Type": 0
            }
          ],
          "Where": [
            {
              "Condition": {
                "In": {
                  "Expressions": [
                    {
                      "Column": {
                        "Expression": {
                          "SourceRef": {
                            "Source": "d"
                          }
                        },
                        "Property": "Actual Only"
                      }
                    }
                  ],
                  "Values": [
                    [
                      {
                        "Literal": {
                          "Value": "'Actual'"
                        }
                      }
                    ],
                    [
                      {
                        "Literal": {
                          "Value": "'Forecast'"
                        }
                      }
                    ]
                  ]
                }
              }
            }
          ]
        }
      }
    ]
  }
}